ultralytics/__init__.py
ultralytics/assets/bus.jpg
ultralytics/assets/zidane.jpg
ultralytics/datasets/Argoverse.yaml
ultralytics/datasets/GlobalWheat2020.yaml
ultralytics/datasets/ImageNet.yaml
ultralytics/datasets/Objects365.yaml
ultralytics/datasets/SKU-110K.yaml
ultralytics/datasets/VOC.yaml
ultralytics/datasets/VisDrone.yaml
ultralytics/datasets/coco-pose.yaml
ultralytics/datasets/coco.yaml
ultralytics/datasets/coco128-seg.yaml
ultralytics/datasets/coco128.yaml
ultralytics/datasets/coco8-pose.yaml
ultralytics/datasets/coco8-seg.yaml
ultralytics/datasets/coco8.yaml
ultralytics/datasets/xView.yaml
ultralytics/hub/__init__.py
ultralytics/hub/auth.py
ultralytics/hub/session.py
ultralytics/hub/utils.py
ultralytics/models/rt-detr/rtdetr-l.yaml
ultralytics/models/rt-detr/rtdetr-x.yaml
ultralytics/models/v3/yolov3-spp.yaml
ultralytics/models/v3/yolov3-tiny.yaml
ultralytics/models/v3/yolov3.yaml
ultralytics/models/v5/yolov5-p6.yaml
ultralytics/models/v5/yolov5.yaml
ultralytics/models/v6/yolov6.yaml
ultralytics/models/v8/yolov8-cls.yaml
ultralytics/models/v8/yolov8-p2.yaml
ultralytics/models/v8/yolov8-p6.yaml
ultralytics/models/v8/yolov8-pose-p6.yaml
ultralytics/models/v8/yolov8-pose.yaml
ultralytics/models/v8/yolov8-rtdetr.yaml
ultralytics/models/v8/yolov8-seg.yaml
ultralytics/models/v8/yolov8.yaml
ultralytics/nn/__init__.py
ultralytics/nn/autobackend.py
ultralytics/nn/autoshape.py
ultralytics/nn/tasks.py
ultralytics/nn/modules/__init__.py
ultralytics/nn/modules/block.py
ultralytics/nn/modules/conv.py
ultralytics/nn/modules/head.py
ultralytics/nn/modules/transformer.py
ultralytics/nn/modules/utils.py
ultralytics/tracker/__init__.py
ultralytics/tracker/track.py
ultralytics/tracker/cfg/botsort.yaml
ultralytics/tracker/cfg/bytetrack.yaml
ultralytics/tracker/trackers/__init__.py
ultralytics/tracker/trackers/basetrack.py
ultralytics/tracker/trackers/bot_sort.py
ultralytics/tracker/trackers/byte_tracker.py
ultralytics/tracker/utils/__init__.py
ultralytics/tracker/utils/gmc.py
xn_ultralytics-1.0.3.dist-info/LICENSE
xn_ultralytics-1.0.3.dist-info/METADATA
xn_ultralytics-1.0.3.dist-info/WHEEL
xn_ultralytics-1.0.3.dist-info/entry_points.txt
xn_ultralytics-1.0.3.dist-info/top_level.txt
xn_ultralytics-1.0.3.dist-info/RECORD
